ip2c/__init__.py
ip2c/main.py
ip2c/requirements.txt
ip2c/serve.py
ip2c/model/ip2country.py
ip2c/model/iprange.py
ip2c-0.1.2.dist-info/entry_points.txt
ip2c-0.1.2.dist-info/LICENSE
ip2c-0.1.2.dist-info/WHEEL
ip2c-0.1.2.dist-info/METADATA
ip2c-0.1.2.dist-info/RECORD
