Metadata-Version: 2.1
Name: ip2c
Version: 0.1.2
Summary: Another IPv4 address to Country Mapper, using IP2Location free database
Home-page: https://github.com/itzmeanjan/ip2country
License: UNKNOWN
Author: Anjan Roy
Author-email: anjanroy@yandex.com
Requires-Python: >=3.7
Classifier: License :: OSI Approved :: MIT License
